typerassistant/__init__.py
typerassistant/assistant.py
typerassistant/py.typed
typerassistant/spec.py
typerassistant/typer.py
typerassistant-0.3.1.dist-info/LICENSE
typerassistant-0.3.1.dist-info/METADATA
typerassistant-0.3.1.dist-info/WHEEL
typerassistant-0.3.1.dist-info/RECORD
