Metadata-Version: 2.1
Name: typerassistant
Version: 0.3.1
Summary: Automatically generate an OpenAI Assistant interface for any python typer CLI.
Home-page: https://github.com/eblume/TyperAssistant
License: MIT
Keywords: typer,openai,assistant,cli,command-line,interface,ai,artificial intelligence
Author: Erich Blume
Author-email: blume.erich@gmail.com
Requires-Python: >=3.10,<4.0
Classifier: Development Status :: 3 - Alpha
Classifier: Environment :: Console
Classifier: Intended Audience :: Developers
Classifier: License :: OSI Approved :: MIT License
Classifier: Operating System :: OS Independent
Classifier: Programming Language :: Python :: 3
Classifier: Programming Language :: Python :: 3.10
Classifier: Programming Language :: Python :: 3.11
Classifier: Programming Language :: Python :: 3.12
Classifier: Topic :: Software Development :: Libraries :: Python Modules
Classifier: Topic :: Software Development :: User Interfaces
Classifier: Topic :: Utilities
Requires-Dist: openai (>=1.3.2,<2.0.0)
Requires-Dist: rich (>=13.7.0,<14.0.0)
Requires-Dist: typer[all] (>=0.9.0,<0.10.0)
Project-URL: Repository, https://github.com/eblume/TyperAssistant
